{
  "cpuCores": 1,
  "ftpPortOpen": false,
  "hasAdminRights": true,
  "hostname": "home",
  "httpPortOpen": false,
  "ip": "66.3.4.6",
  "isConnectedTo": true,
  "maxRam": 8,
  "organizationName": "Home PC",
  "ramUsed": 3.65,
  "smtpPortOpen": false,
  "sqlPortOpen": false,
  "sshPortOpen": false,
  "purchasedByPlayer": true,
  "backdoorInstalled": false,
  "baseDifficulty": 1,
  "hackDifficulty": 1,
  "minDifficulty": 1,
  "moneyAvailable": 0,
  "moneyMax": 0,
  "numOpenPortsRequired": 5,
  "openPortCount": 0,
  "requiredHackingSkill": 1,
  "serverGrowth": 1
}